calculator_6a16205c5a683383/__init__.py
calculator_6a16205c5a683383/calculator.py
calculator_6a16205c5a683383-0.0.3.dist-info/LICENSE
calculator_6a16205c5a683383-0.0.3.dist-info/METADATA
calculator_6a16205c5a683383-0.0.3.dist-info/WHEEL
calculator_6a16205c5a683383-0.0.3.dist-info/top_level.txt
calculator_6a16205c5a683383-0.0.3.dist-info/RECORD
