Metadata-Version: 2.1
Name: calculator_6a16205c5a683383
Version: 0.0.3
Summary: An evil calculator package
Author-email: Tsuto <jacob@jseis.me>
Classifier: Programming Language :: Python :: 3
Classifier: License :: OSI Approved :: MIT License
Classifier: Operating System :: OS Independent
Requires-Python: >=3.7
License-File: LICENSE
